setup.py
IBGelf/__init__.py
IBGelf/handler.py
IBGelf.egg-info/PKG-INFO
IBGelf.egg-info/SOURCES.txt
IBGelf.egg-info/dependency_links.txt
IBGelf.egg-info/top_level.txt
ibgelf/__init__.py
ibgelf/handler.py