Metadata-Version: 1.0
Name: IBGelf
Version: 0.0.6
Summary: Base on GELF for graylog2, added functionality of additional fields
Home-page: http://packages.python.org/IBGelf
Author: Izabel Jelenic
Author-email: izabel.jelenic@infobip.com
License: BSD
Keywords: graypy2 GELF graypy logging
Platform: UNKNOWN
